README.md
setup.cfg
setup.py
regressionAlgorithm/__init__.py
regressionAlgorithm/polynomial_1.py
regressionAlgorithm/polynomial_2.py
regressionAlgorithm.egg-info/PKG-INFO
regressionAlgorithm.egg-info/SOURCES.txt
regressionAlgorithm.egg-info/dependency_links.txt
regressionAlgorithm.egg-info/requires.txt
regressionAlgorithm.egg-info/top_level.txt