Metadata-Version: 2.1
Name: regressionAlgorithm
Version: 0.1
Summary: Linear Regression Algorithm
Home-page: https://github.com/rizki4106/regressionAlgorithm
Author: Rizki Maulana
Author-email: rizkimaulana348@gmail.com
License: MIT
Download-URL: https://github.com/rizki4106/regressionAlgorithm/v_01.tar.gz
Keywords: linear-regression,machine-learning,supervise-learning
Platform: UNKNOWN
Classifier: Development Status :: 4 - Beta
Classifier: Intended Audience :: Developers
Classifier: Topic :: Software Development :: Build Tools
Classifier: License :: OSI Approved :: MIT License
Classifier: Programming Language :: Python :: 3
Classifier: Programming Language :: Python :: 3.4
Classifier: Programming Language :: Python :: 3.5
Classifier: Programming Language :: Python :: 3.6
